pupu/__init__.py
pupu/blue.py
pupu/green.py
pupu/purple.py
pupu-0.1.0.dist-info/METADATA
pupu-0.1.0.dist-info/WHEEL
pupu-0.1.0.dist-info/top_level.txt
pupu-0.1.0.dist-info/RECORD
