Metadata-Version: 2.4
Name: pupu
Version: 0.1.0
Summary: Package containing blue.py, green.py, and purple.py files
Author: Amex005
Classifier: Programming Language :: Python :: 3
Classifier: Operating System :: OS Independent
Requires-Python: >=3.7
Requires-Dist: PySide6
Requires-Dist: pandas
Dynamic: author
Dynamic: classifier
Dynamic: requires-dist
Dynamic: requires-python
Dynamic: summary
